mcp_sqlalchemy_server/__init__.py
mcp_sqlalchemy_server/server.py
mseep_mcp_sqlalchemy_server-0.3.3.dist-info/licenses/LICENSE
mseep_mcp_sqlalchemy_server-0.3.3.dist-info/METADATA
mseep_mcp_sqlalchemy_server-0.3.3.dist-info/WHEEL
mseep_mcp_sqlalchemy_server-0.3.3.dist-info/entry_points.txt
mseep_mcp_sqlalchemy_server-0.3.3.dist-info/top_level.txt
mseep_mcp_sqlalchemy_server-0.3.3.dist-info/RECORD
