Metadata-Version: 2.4
Name: mseep-mcp-sqlalchemy-server
Version: 0.3.3
Summary: A simple MCP ODBC server using FastAPI and ODBC
Home-page: 
Author: mseep
Author-email: mseep <support@skydeck.ai>
Maintainer-email: mseep <support@skydeck.ai>
Requires-Python: >=3.6
License-File: LICENSE
Requires-Dist: mcp[cli]>=1.4.1
Requires-Dist: pyodbc>=5.2.0
Requires-Dist: python-dotenv>=1.0.1
Dynamic: author
Dynamic: license-file
Dynamic: requires-python
